LICENSE
MANIFEST.in
README.rst
setup.cfg
setup.py
django_tracking_analyzer_django2.egg-info/PKG-INFO
django_tracking_analyzer_django2.egg-info/SOURCES.txt
django_tracking_analyzer_django2.egg-info/dependency_links.txt
django_tracking_analyzer_django2.egg-info/requires.txt
django_tracking_analyzer_django2.egg-info/top_level.txt
tracking_analyzer/__init__.py
tracking_analyzer/admin.py
tracking_analyzer/apps.py
tracking_analyzer/compat.py
tracking_analyzer/conf.py
tracking_analyzer/manager.py
tracking_analyzer/models.py
tracking_analyzer/management/__init__.py
tracking_analyzer/management/commands/__init__.py
tracking_analyzer/management/commands/install_geoip_dataset.py
tracking_analyzer/migrations/0001_initial.py
tracking_analyzer/migrations/0002_auto_20160719_2212.py
tracking_analyzer/migrations/__init__.py
tracking_analyzer/static/admin/css/d3-tip.css
tracking_analyzer/static/admin/css/main.css
tracking_analyzer/static/admin/js/devices_stats.js
tracking_analyzer/static/admin/js/requests_graph.js
tracking_analyzer/static/admin/js/world_map.js
tracking_analyzer/static/admin/js/vendor/d3/LICENSE
tracking_analyzer/static/admin/js/vendor/d3/d3.min.js
tracking_analyzer/static/admin/js/vendor/d3-tip/LICENSE
tracking_analyzer/static/admin/js/vendor/d3-tip/d3-tip.min.js
tracking_analyzer/static/admin/js/vendor/datamaps/LICENSE
tracking_analyzer/static/admin/js/vendor/datamaps/datamaps.world.min.js
tracking_analyzer/static/admin/js/vendor/topojson/LICENSE
tracking_analyzer/static/admin/js/vendor/topojson/topojson.min.js
tracking_analyzer/templates/admin/tracking_analyzer/tracker/change_list.html