Metadata-Version: 1.1
Name: django-tracking-analyzer-django2
Version: 0.3
Summary: User actions tracking and analytics for Django sites.
Home-page: https://github.com/jose-lpa/django-tracking-analyzer
Author: José Luis Patiño Andrés / cr0hn
Author-email: cr0hn@cr0hn.com
License: UNKNOWN
Keywords: django,analytics,web,monitoring,logging
Platform: UNKNOWN
Classifier: Development Status :: 5 - Production/Stable
Classifier: Framework :: Django
Classifier: Intended Audience :: Developers
Classifier: License :: OSI Approved :: GNU General Public License v3 (GPLv3)
Classifier: Operating System :: Unix
Classifier: Operating System :: MacOS
Classifier: Operating System :: Microsoft :: Windows
Classifier: Programming Language :: Python :: 2.7
Classifier: Programming Language :: Python :: 3.4
Classifier: Programming Language :: Python :: 3.5
Classifier: Topic :: Software Development :: Libraries :: Application Frameworks
Classifier: Topic :: System :: Logging
Classifier: Topic :: System :: Monitoring
Classifier: Topic :: Utilities
